vectra/__init__.py
vectra/callbacks.py
vectra/cli.py
vectra/config.py
vectra/core.py
vectra/evaluation.py
vectra/interfaces.py
vectra/memory.py
vectra/observability.py
vectra/processor.py
vectra/reranker.py
vectra/telemetry.py
vectra/webconfig_server.py
vectra/backends/anthropic.py
vectra/backends/chroma_store.py
vectra/backends/gemini.py
vectra/backends/huggingface.py
vectra/backends/milvus_store.py
vectra/backends/ollama.py
vectra/backends/openai.py
vectra/backends/openrouter.py
vectra/backends/postgres_store.py
vectra/backends/prisma_store.py
vectra/backends/qdrant_store.py
vectra_rag_py-0.9.11.dist-info/licenses/LICENSE
vectra_rag_py-0.9.11.dist-info/METADATA
vectra_rag_py-0.9.11.dist-info/WHEEL
vectra_rag_py-0.9.11.dist-info/entry_points.txt
vectra_rag_py-0.9.11.dist-info/top_level.txt
vectra_rag_py-0.9.11.dist-info/RECORD
