Metadata-Version: 2.4
Name: vectra-rag-py
Version: 0.9.11
Summary: A production-ready, provider-agnostic Python SDK for End-to-End RAG pipelines.
Author-email: Abhishek N <astroabhi.abhi@gmail.com>
License: MIT
Project-URL: Homepage, https://github.com/iamabhishek-n/vectra-py
Project-URL: Issues, https://github.com/iamabhishek-n/vectra-py/issues
Keywords: rag,llm,openai,anthropic,gemini,vector-database,vectrasdk
Classifier: Programming Language :: Python :: 3
Classifier: License :: OSI Approved :: GNU General Public License v3 (GPLv3)
Classifier: Operating System :: OS Independent
Requires-Python: >=3.8
License-File: LICENSE
Requires-Dist: pypdf
Requires-Dist: mammoth
Requires-Dist: openpyxl
Requires-Dist: openai
Requires-Dist: google-genai
Requires-Dist: anthropic
Requires-Dist: pydantic
Requires-Dist: prisma
Requires-Dist: chromadb
Requires-Dist: requests
Requires-Dist: asyncpg
Dynamic: license-file
